Metadata-Version: 1.1
Name: envconfig
Version: 0.2.1
Summary: Parse config options from the OS environment.
Home-page: https://github.com/dbader/envconfig
Author: Daniel Bader
Author-email: mail@dbader.org
License: MIT
Download-URL: https://github.com/dbader/envconfig/tarball/0.2.1
Keywords: config,environment,12factor
Platform: UNKNOWN
Classifier: Intended Audience :: Developers
Classifier: License :: OSI Approved :: MIT License
Classifier: Programming Language :: Python :: 2.7
Classifier: Programming Language :: Python :: 3
Classifier: Natural Language :: English
